LICENSE
README.md
setup.py
psrt/__init__.py
psrt.egg-info/PKG-INFO
psrt.egg-info/SOURCES.txt
psrt.egg-info/dependency_links.txt
psrt.egg-info/top_level.txt